myfy_cli/__init__.py
myfy_cli/asgi_factory.py
myfy_cli/main.py
myfy_cli/version.py
myfy_cli/commands/__init__.py
myfy_cli/commands/frontend.py
myfy_cli-0.1.2.dist-info/METADATA
myfy_cli-0.1.2.dist-info/WHEEL
myfy_cli-0.1.2.dist-info/entry_points.txt
myfy_cli-0.1.2.dist-info/RECORD
