Metadata-Version: 2.4
Name: myfy-cli
Version: 0.1.2
Summary: CLI tools for myfy framework
Requires-Python: >=3.12
Requires-Dist: klyne>=0.3.0
Requires-Dist: myfy-core~=0.1.2
Requires-Dist: rich>=13.0
Requires-Dist: typer>=0.12
Requires-Dist: uvicorn[standard]>=0.30
Provides-Extra: production
Requires-Dist: gunicorn>=22.0.0; extra == 'production'
